{"algorithm_data-structure.md":"4b42bbab","algorithm_heap.md":"a7ab5fbd","advanced_design-patterns.md":"0b992e3d","algorithm_stack.md":"e70fc376","advanced_reg-exp.md":"713b5e5f","advanced_framework.md":"f48d177b","algorithm_recursion.md":"1b937cd4","algorithm_index.md":"b097c997","framework_micro-frontend_knowledge.md":"3bc83f8f","columns_perform-optimize_index.md":"f1882ca7","framework_miniprogram_knowledge.md":"5c52a3e4","framework_micro-frontend_single-spa.md":"5761bdca","framework_react_code.md":"c8151eaa","framework_react_index.md":"fb296f97","framework_react_knowledge.md":"32ddb403","index.md":"b81962d2","framework_vue_knowledge.md":"54505e96","interview_optimization.md":"006b1013","framework_vue_code.md":"34a577d5","language_typescript.md":"45662bc2","framework_vue_index.md":"55806c5f","interview_index.md":"0e24dc22","interview_restful.md":"555dad36","links_blogs.md":"447eb90d","mini-code_micro-frontend.md":"331bc294","mini-code_promise.md":"dc16343b","mini-code_vue-next-mini_runtime-dom.md":"eb888a1c","mini-code_vue2.md":"7a41db67","bundle_esbuild.md":"20d47789","links_plugins.md":"969eea36","qa_index.md":"02156584","mini-code_vue-next-mini_reactivity.md":"95d7fb12","webpack_index.md":"9e872a25","algorithm_binary-tree.md":"d8d818ec","mini-code_vue-next-mini_runtime-core.md":"7b955536","mini-code_vue-next-mini_compiler-core.md":"be447b05","language_javascript.md":"dd531434","mini-code_vue3.md":"4cdaa7cd","mini-code_vue-router.md":"31f3416f","links_projects.md":"9ac9737e","framework_micro-frontend_module-federation.md":"e10f859d","bundle_webpack.md":"3c7728cf","bundle_vite.md":"2fd54fd7","algorithm_sort.md":"c3edbe73","bundle_rollup.md":"f245265f","links_websites.md":"c2210dc3","mini-code_vue-next-mini_compiler-dom.md":"0d5a35c1","algorithm_kmp.md":"bb1d3f66","columns_micro-frontend_index.md":"09ce3267","algorithm_queue.md":"e98e36cd","advanced_cli_index.md":"3e10e927"}
